setup.py
aiLearning/Feature.py
aiLearning/__init__.py
aiLearning.egg-info/PKG-INFO
aiLearning.egg-info/SOURCES.txt
aiLearning.egg-info/dependency_links.txt
aiLearning.egg-info/top_level.txt
aiLearning.egg-info/zip-safe